streamlit_telegram_login/__init__.py
streamlit_telegram_login/helpers.py
streamlit_telegram_login/frontend/index.html
streamlit_telegram_login/frontend/main.js
streamlit_telegram_login/frontend/package.json
streamlit_telegram_login/frontend/streamlit-component-lib.js
streamlit_telegram_login/frontend/style.css
streamlit_telegram_login/frontend/vite.config.js
streamlit_telegram_login-0.0.3.dist-info/LICENSE
streamlit_telegram_login-0.0.3.dist-info/METADATA
streamlit_telegram_login-0.0.3.dist-info/WHEEL
streamlit_telegram_login-0.0.3.dist-info/top_level.txt
streamlit_telegram_login-0.0.3.dist-info/RECORD
