Metadata-Version: 2.1
Name: streamlit-telegram-login
Version: 0.0.3
Summary: Streamlit component that implements a telegram bot widget
Home-page: https://github.com/berkutsoft/streamlit-telegram-login
Author: Berkutsoft 11
Author-email: berkut1011@gmail.com
Requires-Python: >=3.8
License-File: LICENSE
Requires-Dist: streamlit >=1.28.0
Requires-Dist: jinja2
Requires-Dist: PyYAML >=5.3.1
Requires-Dist: extra-streamlit-components >=0.1.60
Requires-Dist: PyJWT >=2.8.0
